twitter_analysis.py
twitter_analysis-0.0.5.dist-info/DESCRIPTION.rst
twitter_analysis-0.0.5.dist-info/METADATA
twitter_analysis-0.0.5.dist-info/RECORD
twitter_analysis-0.0.5.dist-info/WHEEL
twitter_analysis-0.0.5.dist-info/metadata.json
twitter_analysis-0.0.5.dist-info/top_level.txt
