Metadata-Version: 2.0
Name: twitter-analysis
Version: 0.0.5
Summary: Get tweets from the Twitter Frontend API.
Home-page: https://github.com/ferguras/twitter-analysis
Author: Edwin de Haan
Author-email: twitter@solarwar.org
License: MIT
Platform: UNKNOWN
Classifier: License :: OSI Approved :: MIT License
Classifier: Programming Language :: Python
Classifier: Programming Language :: Python :: 3.6
Classifier: Programming Language :: Python :: Implementation :: CPython
Classifier: Programming Language :: Python :: Implementation :: PyPy
Requires-Dist: requests-html
